zinc_cli/__init__.py
zinc_cli/zinc.py
zinc_cli/commands/__init__.py
zinc_cli/commands/zinc_transform.py
zinc_cli/commands/aws_util/__init__.py
zinc_cli/commands/aws_util/aws_utils.py
zinc_cli/commands/create/__init__.py
zinc_cli/commands/create/create_infrastructure.py
zinc_cli/commands/create/zinc_create.py
zinc_cli/commands/create/zinc_create_request.py
zinc_cli/commands/create/contact_api/__init__.py
zinc_cli/commands/create/contact_api/create_contact_api_cmd.py
zinc_cli/commands/create/contact_api/create_contact_api_request.py
zinc_cli/commands/create/crud_api/__init__.py
zinc_cli/commands/create/crud_api/create_crud_api_cmd.py
zinc_cli/commands/create/crud_api/create_crud_api_request.py
zinc_cli/commands/create/domain/__init__.py
zinc_cli/commands/create/domain/domain_manager.py
zinc_cli/commands/create/domain/hosted_zone_manager.py
zinc_cli/commands/create/project/__init__.py
zinc_cli/commands/create/project/create_project_cmd.py
zinc_cli/commands/create/project/create_project_request.py
zinc_cli/commands/create/static_site/__init__.py
zinc_cli/commands/create/static_site/create_static_site_cmd.py
zinc_cli/commands/create/static_site/create_static_site_request.py
zinc_cli/infrastructure/__init__.py
zinc_cli/infrastructure/cdk.context.json
zinc_cli/infrastructure/cdk.json
zinc_cli/infrastructure/infrastructure.py
zinc_cli/infrastructure/models/__init__.py
zinc_cli/infrastructure/models/infrastructure_service_field.py
zinc_cli/infrastructure/models/infrastructure_service_model.py
zinc_cli/infrastructure/services/__init__.py
zinc_cli/infrastructure/services/master_stack.py
zinc_cli/infrastructure/services/base_lambda/__init__.py
zinc_cli/infrastructure/services/base_lambda/copy_utils_to_services.py
zinc_cli/infrastructure/services/base_lambda/util_src/__init__.py
zinc_cli/infrastructure/services/base_lambda/util_src/crud_api.py
zinc_cli/infrastructure/services/base_lambda/util_src/crud_builder.py
zinc_cli-0.3.1.dist-info/METADATA
zinc_cli-0.3.1.dist-info/WHEEL
zinc_cli-0.3.1.dist-info/entry_points.txt
zinc_cli-0.3.1.dist-info/top_level.txt
zinc_cli-0.3.1.dist-info/RECORD
