Metadata-Version: 2.1
Name: zinc-cli
Version: 0.3.1
Summary: Package Description.
Home-page: https://github.com/krinj
Author: Jakrin Juangbhanich
Author-email: juangbhanich.k@gmail.com
License: UNKNOWN
Platform: UNKNOWN
Classifier: Programming Language :: Python :: 3.7
Requires-Dist: botocore
Requires-Dist: pyyaml
Requires-Dist: boto3
Requires-Dist: kix
Requires-Dist: aws-cdk.core (==1.159)
Requires-Dist: aws-cdk.aws-lambda (==1.159)
Requires-Dist: aws-cdk.aws-route53 (==1.159)
Requires-Dist: aws-cdk.aws-s3 (==1.159)
Requires-Dist: aws-cdk.aws-cloudfront (==1.159)
Requires-Dist: aws-cdk.aws-route53-targets (==1.159)
Requires-Dist: aws-cdk.aws-s3-deployment (==1.159)
Requires-Dist: aws-cdk.aws-dynamodb (==1.159)
Requires-Dist: aws-cdk.aws-iam (==1.159)
Requires-Dist: aws-cdk.aws-cognito (==1.159)
Requires-Dist: aws-cdk.custom-resources (==1.159)
